<?xml version="1.0" encoding="UTF-8"?>
<bmwprov>
<version>5.0</version>
<id>0-0</id>
<validity>2592000</validity>
<cmd>delete</cmd>
<as>
<key>
<smcc>000</smcc>
<smnc>000</smnc>
<nmcc>000</nmcc>
<nmnc>000</nmnc>
</key>
<access>
<cm>
<bearer>0E</bearer>
</cm>
<gprs>
<apn/>
<apnuser/>
<apnpwd/>
<qos/>
<pdptype/>
<gprstimeout>600</gprstimeout>
</gprs>
</access>
<portal>
<http>
<proxy>**YOUR PROXY IP**</proxy>
<port>8080</port>
<proxyuser>b2v_standard</proxyuser>
<proxypwd>b2v_standard</proxypwd>
</http>
<dumm>
<csdtimeout>0</csdtimeout>
<gprstimeout>600</gprstimeout>
<proxycfgurl/>
</dumm>
<prov>
<url>http://127.0.0.1/provision.php</url>
</prov>
<bon>
<url>http://127.0.0.1/bonstartpage.php</url>
<disable>00</disable>
<vmax>FF</vmax>
<csdtimeout>0</csdtimeout>
<gprstimeout>600</gprstimeout>
</bon>
</portal>
</as>
<cl>
<acl>
<aclappl>
<appname>prov</appname>
<appcode>2</appcode>
<minbearer>0E</minbearer>
<maxbearer>0E</maxbearer>
<voicechannel>0</voicechannel>
<datachannel>1</datachannel>
<csd_no>0</csd_no>
<sms_a>0</sms_a>
<inband>0</inband>
<priority>1</priority>
<vehauthlevel>1</vehauthlevel>
<userauth>0</userauth>
<freeinternetmode>0</freeinternetmode>
<setinternet>0</setinternet>
<provmode>1</provmode>
<roaming>1</roaming>
<exclusive>0</exclusive>
<setexclusive>0</setexclusive>
<showhmi>1</showhmi>
<seccomponent>0</seccomponent>
<mt>0</mt>
<mo>0</mo>
<clampfollowup>0</clampfollowup>
<audio>0</audio>
<dummmode>0</dummmode>
</aclappl>
<aclappl>
<appname>prov</appname>
<appcode>2</appcode>
<minbearer>0E</minbearer>
<maxbearer>0E</maxbearer>
<voicechannel>0</voicechannel>
<datachannel>1</datachannel>
<csd_no>0</csd_no>
<sms_a>0</sms_a>
<inband>0</inband>
<priority>1</priority>
<vehauthlevel>1</vehauthlevel>
<userauth>0</userauth>
<freeinternetmode>0</freeinternetmode>
<setinternet>0</setinternet>
<provmode>0</provmode>
<roaming>1</roaming>
<exclusive>0</exclusive>
<setexclusive>0</setexclusive>
<showhmi>1</showhmi>
<seccomponent>0</seccomponent>
<mt>0</mt>
<mo>0</mo>
<clampfollowup>0</clampfollowup>
<audio>0</audio>
<dummmode>0</dummmode>
</aclappl>
<aclappl>
<appname>prov</appname>
<appcode>2</appcode>
<minbearer>0E</minbearer>
<maxbearer>0E</maxbearer>
<voicechannel>0</voicechannel>
<datachannel>2</datachannel>
<csd_no>0</csd_no>
<sms_a>0</sms_a>
<inband>0</inband>
<priority>1</priority>
<vehauthlevel>1</vehauthlevel>
<userauth>0</userauth>
<freeinternetmode>0</freeinternetmode>
<setinternet>0</setinternet>
<provmode>0</provmode>
<roaming>1</roaming>
<exclusive>0</exclusive>
<setexclusive>0</setexclusive>
<showhmi>1</showhmi>
<seccomponent>0</seccomponent>
<mt>0</mt>
<mo>0</mo>
<clampfollowup>0</clampfollowup>
<audio>1</audio>
<dummmode>0</dummmode>
</aclappl>
<aclappl>
<appname>prov</appname>
<appcode>2</appcode>
<minbearer>0E</minbearer>
<maxbearer>0E</maxbearer>
<voicechannel>0</voicechannel>
<datachannel>2</datachannel>
<csd_no>0</csd_no>
<sms_a>0</sms_a>
<inband>0</inband>
<priority>1</priority>
<vehauthlevel>1</vehauthlevel>
<userauth>0</userauth>
<freeinternetmode>0</freeinternetmode>
<setinternet>0</setinternet>
<provmode>1</provmode>
<roaming>1</roaming>
<exclusive>0</exclusive>
<setexclusive>0</setexclusive>
<showhmi>1</showhmi>
<seccomponent>0</seccomponent>
<mt>0</mt>
<mo>0</mo>
<clampfollowup>0</clampfollowup>
<audio>1</audio>
<dummmode>0</dummmode>
</aclappl>
<aclappl>
<appname>bon</appname>
<appcode>3</appcode>
<minbearer>0E</minbearer>
<maxbearer>0E</maxbearer>
<voicechannel>0</voicechannel>
<datachannel>1</datachannel>
<csd_no>0</csd_no>
<sms_a>0</sms_a>
<inband>0</inband>
<priority>3</priority>
<vehauthlevel>1</vehauthlevel>
<userauth>0</userauth>
<freeinternetmode>0</freeinternetmode>
<setinternet>0</setinternet>
<provmode>1</provmode>
<roaming>1</roaming>
<exclusive>0</exclusive>
<setexclusive>0</setexclusive>
<showhmi>1</showhmi>
<seccomponent>0</seccomponent>
<mt>0</mt>
<mo>0</mo>
<clampfollowup>0</clampfollowup>
<audio>0</audio>
<dummmode>0</dummmode>
</aclappl>
<aclappl>
<appname>bon</appname>
<appcode>3</appcode>
<minbearer>0E</minbearer>
<maxbearer>0E</maxbearer>
<voicechannel>0</voicechannel>
<datachannel>2</datachannel>
<csd_no>0</csd_no>
<sms_a>0</sms_a>
<inband>0</inband>
<priority>3</priority>
<vehauthlevel>1</vehauthlevel>
<userauth>0</userauth>
<freeinternetmode>0</freeinternetmode>
<setinternet>0</setinternet>
<provmode>1</provmode>
<roaming>1</roaming>
<exclusive>0</exclusive>
<setexclusive>0</setexclusive>
<showhmi>1</showhmi>
<seccomponent>0</seccomponent>
<mt>0</mt>
<mo>0</mo>
<clampfollowup>0</clampfollowup>
<audio>0</audio>
<dummmode>0</dummmode>
</aclappl>
</acl>
</cl>
<config>
<dummmaxpartsize>10240</dummmaxpartsize>
<dummhttpresponsetimeout>120000</dummhttpresponsetimeout>
<dummuseragent>CIC</dummuseragent>
<dummabortpausetimeout>30000</dummabortpausetimeout>
<dummusegzip>true</dummusegzip>
<dummwaitreestablish>10000</dummwaitreestablish>
<acmwaitreestablish>10</acmwaitreestablish>
<acmmaxreconnretries>2</acmmaxreconnretries>
<pmdownloadretries>1</pmdownloadretries>
<pmretryinterval>120</pmretryinterval>
<pmincludeeprov>true</pmincludeeprov>
</config>
</bmwprov>
